zephyrion/__init__.py
zephyrion/_common/__init__.py
zephyrion/_common/browser_manager.py
zephyrion/playwr/__init__.py
zephyrion/playwr/browser_manager.py
zephyrion/playwr/page_interactor/__init__.py
zephyrion/playwr/page_interactor/_main.py
zephyrion/pypp/__init__.py
zephyrion/pypp/_main.py
zephyrion/pypp/browser_manager.py
zephyrion/pypp/data_extractor.py
zephyrion/pypp/js_util/__init__.py
zephyrion/pypp/js_util/decorator.py
zephyrion/pypp/js_util/interface.py
zephyrion/pypp/js_util/js_generator/__init__.py
zephyrion/pypp/js_util/js_generator/generator.py
zephyrion/pypp/js_util/js_handler/__init__.py
zephyrion/pypp/js_util/js_handler/action_handler/__init__.py
zephyrion/pypp/js_util/js_handler/action_handler/_click_handler.py
zephyrion/pypp/js_util/js_handler/action_handler/_input_handler.py
zephyrion/pypp/js_util/js_handler/action_handler/_scroll_handler.py
zephyrion/pypp/js_util/js_handler/action_handler/common.py
zephyrion/pypp/js_util/js_handler/data_handler/__init__.py
zephyrion/pypp/js_util/js_handler/data_handler/common.py
zephyrion/pypp/page_interactor/__init__.py
zephyrion/pypp/page_interactor/_config.py
zephyrion/pypp/page_interactor/_decorator.py
zephyrion/pypp/page_interactor/_main.py
zephyrion-0.1.18.dist-info/LICENCE
zephyrion-0.1.18.dist-info/METADATA
zephyrion-0.1.18.dist-info/WHEEL
zephyrion-0.1.18.dist-info/top_level.txt
zephyrion-0.1.18.dist-info/RECORD
