Metadata-Version: 2.1
Name: zephyrion
Version: 0.1.18
Home-page: https://github.com/stevieflyer/zephyrion
Author: steveflyer
Author-email: steveflyer7@gmail.com
License-File: LICENCE
Requires-Dist: gembox
Requires-Dist: pyppeteer
